<?xml version="1.0" encoding="utf-8"?><rows>
  <row alias="total">
    <cell alias="rowNum" colSpan="1" rowSpan="1" styleAlias="Контрольные суммы"/>
    <cell alias="fix" colSpan="5" rowSpan="1" stringValue="Общий итог" styleAlias="Контрольные суммы"/>
    <cell alias="subject" colSpan="1" rowSpan="1" styleAlias="Контрольные суммы"/>
    <cell alias="taxAuthority" colSpan="1" rowSpan="1" styleAlias="Контрольные суммы"/>
    <cell alias="kpp" colSpan="1" rowSpan="1" styleAlias="Контрольные суммы"/>
    <cell alias="oktmo" colSpan="1" rowSpan="1" styleAlias="Контрольные суммы"/>
    <cell alias="address" colSpan="1" rowSpan="1" styleAlias="Контрольные суммы"/>
    <cell alias="sign" colSpan="1" rowSpan="1" styleAlias="Контрольные суммы"/>
    <cell alias="cadastreNum" colSpan="1" rowSpan="1" styleAlias="Контрольные суммы"/>
    <cell alias="cadastrePriceJanuary" colSpan="1" rowSpan="1" styleAlias="Контрольные суммы"/>
    <cell alias="cadastrePriceTaxFree" colSpan="1" rowSpan="1" styleAlias="Контрольные суммы"/>
    <cell alias="tenure" colSpan="1" rowSpan="1" styleAlias="Контрольные суммы"/>
    <cell alias="taxBenefitCode" colSpan="1" rowSpan="1" styleAlias="Контрольные суммы"/>
    <cell alias="taxBase" colSpan="1" rowSpan="1" styleAlias="Контрольные суммы"/>
    <cell alias="taxRate" colSpan="1" rowSpan="1" styleAlias="Контрольные суммы"/>
    <cell alias="sum" colSpan="1" rowSpan="1" styleAlias="Контрольные суммы"/>
    <cell alias="periodSum" colSpan="1" rowSpan="1" styleAlias="Контрольные суммы"/>
    <cell alias="reductionPaymentSum" colSpan="1" rowSpan="1" styleAlias="Контрольные суммы"/>
  </row>
</rows>
