<?xml version="1.0" encoding="utf-8"?><rows><row alias="1"><cell alias="number" colSpan="6" rowSpan="1" stringValue="1. Субфедеральные и муниципальные облигации, за исключением муниципальных облигаций, выпущенных до 1 января 2007 года на срок не менее 3 лет (15%)" styleAlias="Раздел 2 уровня"/><cell alias="name" colSpan="1" rowSpan="1"/><cell alias="code" colSpan="1" rowSpan="1"/><cell alias="cost" colSpan="1" rowSpan="1"/><cell alias="bondsCount" colSpan="1" rowSpan="1"/><cell alias="percent" colSpan="1" rowSpan="1"/></row><row alias="2"><cell alias="number" colSpan="6" rowSpan="1" stringValue="2. Муниципальные облигации, выпущенные до 1 января 2007 года на срок не менее 3 лет (9%)" styleAlias="Раздел 2 уровня"/><cell alias="name" colSpan="1" rowSpan="1" stringValue=""/><cell alias="code" colSpan="1" rowSpan="1"/><cell alias="cost" colSpan="1" rowSpan="1"/><cell alias="bondsCount" colSpan="1" rowSpan="1"/><cell alias="percent" colSpan="1" rowSpan="1"/></row><row alias="3"><cell alias="number" colSpan="6" rowSpan="1" stringValue="3. Ипотечные облигации, выпущенные до 1 января 2007 года (9%)" styleAlias="Раздел 2 уровня"/><cell alias="name" colSpan="1" rowSpan="1"/><cell alias="code" colSpan="1" rowSpan="1"/><cell alias="cost" colSpan="1" rowSpan="1"/><cell alias="bondsCount" colSpan="1" rowSpan="1"/><cell alias="percent" colSpan="1" rowSpan="1"/></row><row alias="4"><cell alias="number" colSpan="6" rowSpan="1" stringValue="4. Ипотечные облигации, выпущенные после 1 января 2007 года (15%)" styleAlias="Раздел 2 уровня"/><cell alias="name" colSpan="1" rowSpan="1"/><cell alias="code" colSpan="1" rowSpan="1"/><cell alias="cost" colSpan="1" rowSpan="1"/><cell alias="bondsCount" colSpan="1" rowSpan="1"/><cell alias="percent" colSpan="1" rowSpan="1"/></row><row alias="5"><cell alias="number" colSpan="6" rowSpan="1" stringValue="5. Корпоративные облигации (20%)" styleAlias="Раздел 2 уровня"/><cell alias="name" colSpan="1" rowSpan="1"/><cell alias="code" colSpan="1" rowSpan="1"/><cell alias="cost" colSpan="1" rowSpan="1"/><cell alias="bondsCount" colSpan="1" rowSpan="1"/><cell alias="percent" colSpan="1" rowSpan="1"/></row><row alias="6"><cell alias="number" colSpan="6" rowSpan="1" stringValue="6. Прочие еврооблигации (20%)" styleAlias="Раздел 2 уровня"/><cell alias="name" colSpan="1" rowSpan="1"/><cell alias="code" colSpan="1" rowSpan="1"/><cell alias="cost" colSpan="1" rowSpan="1"/><cell alias="bondsCount" colSpan="1" rowSpan="1"/><cell alias="percent" colSpan="1" rowSpan="1"/></row><row alias="7"><cell alias="number" colSpan="6" rowSpan="1" stringValue="7. Государственные облигации Республики Беларусь (15%)" styleAlias="Раздел 2 уровня"/><cell alias="name" colSpan="1" rowSpan="1" stringValue=""/><cell alias="code" colSpan="1" rowSpan="1"/><cell alias="cost" colSpan="1" rowSpan="1"/><cell alias="bondsCount" colSpan="1" rowSpan="1"/><cell alias="percent" colSpan="1" rowSpan="1"/></row><row alias="8"><cell alias="number" colSpan="6" rowSpan="1" stringValue="8. Еврооблигации РФ (20%)" styleAlias="Раздел 2 уровня"/><cell alias="name" colSpan="1" rowSpan="1" stringValue=""/><cell alias="code" colSpan="1" rowSpan="1"/><cell alias="cost" colSpan="1" rowSpan="1"/><cell alias="bondsCount" colSpan="1" rowSpan="1"/><cell alias="percent" colSpan="1" rowSpan="1"/></row></rows>